[{"domain": ".taobao.com", "httpOnly": false, "name": "_tb_token_", "path": "/", "sameSite": "None", "secure": true, "value": "7678568b16588"}, {"domain": ".taobao.com", "httpOnly": true, "name": "_samesite_flag_", "path": "/", "sameSite": "None", "secure": true, "value": "true"}, {"domain": "login.taobao.com", "httpOnly": true, "name": "XSRF-TOKEN", "path": "/", "secure": false, "value": "e68ba9d0-d2e2-4251-80e5-7a0f63a590ea"}, {"domain": ".taobao.com", "expiry": 1613096936, "httpOnly": false, "name": "_m_h5_tk_enc", "path": "/", "sameSite": "None", "secure": true, "value": "25043c9b74cd22f85c50ef2fc5881395"}, {"domain": ".taobao.com", "expiry": 1613096936, "httpOnly": false, "name": "_m_h5_tk", "path": "/", "sameSite": "None", "secure": true, "value": "927555ec0efd4259fdced699b89903f2_1612499697101"}, {"domain": ".taobao.com", "expiry": 1612578536, "httpOnly": false, "name": "xlly_s", "path": "/", "sameSite": "None", "secure": true, "value": "1"}, {"domain": ".taobao.com", "expiry": 1644007257, "httpOnly": false, "name": "_cc_", "path": "/", "sameSite": "None", "secure": true, "value": "WqG3DMC9EA%3D%3D"}, {"domain": "login.taobao.com", "expiry": 1926635986, "httpOnly": false, "name": "_uab_collina", "path": "/member", "secure": false, "value": "161127598640468729150445"}, {"domain": ".taobao.com", "expiry": 1615063257, "httpOnly": true, "name": "uc4", "path": "/", "sameSite": "None", "secure": true, "value": "nk4=0%40r4kScdWsWyf460N7j3Iqz4ViUw%3D%3D&id4=0%40U2gvKU%2FKIg0kGn76FJB4PTjrGICl"}, {"domain": ".taobao.com", "httpOnly": true, "name": "cookie2", "path": "/", "sameSite": "None", "secure": true, "value": "1691c56d72833f9dff2f142aa0c37e07"}, {"domain": ".taobao.com", "expiry": 1644007257, "httpOnly": false, "name": "sgcookie", "path": "/", "sameSite": "None", "secure": true, "value": "E100%2F3F%2FsZ9aaJ%2Fo%2FSMe%2FZtrvxEjr9JQJe7a9iuczY6JSS%2BpwVe43%2FlLmp3ZZrf2bkLuQ8Oqo4k413mGqJR5BU7p3A%3D%3D"}, {"domain": ".taobao.com", "expiry": 1615063257, "httpOnly": false, "name": "lgc", "path": "/", "sameSite": "None", "secure": true, "value": "%5Cu543E%5Cu540D%5Cu5B50%5Cu6851"}, {"domain": ".taobao.com", "expiry": 1613063286, "httpOnly": false, "name": "mt", "path": "/", "sameSite": "None", "secure": true, "value": "ci=75_1"}, {"domain": ".taobao.com", "expiry": 1644007257, "httpOnly": false, "name": "tracknick", "path": "/", "sameSite": "None", "secure": true, "value": "%5Cu543E%5Cu540D%5Cu5B50%5Cu6851"}, {"domain": ".login.taobao.com", "expiry": 1644007257, "httpOnly": false, "name": "lid", "path": "/", "sameSite": "None", "secure": true, "value": "%E5%90%BE%E5%90%8D%E5%AD%90%E6%A1%91"}, {"domain": ".taobao.com", "expiry": 1615063257, "httpOnly": true, "name": "uc3", "path": "/", "sameSite": "None", "secure": true, "value": "lg2=URm48syIIVrSKA%3D%3D&vt3=F8dCuAc7kzO6z2opdkg%3D&nk2=rXiYs3lchTI%3D&id2=UUplZkUMQ%2B2DuA%3D%3D"}, {"domain": ".taobao.com", "expiry": 1628045509, "httpOnly": false, "name": "l", "path": "/", "secure": false, "value": "eBE-UmxPOvXaP5GzBOfZnurza779sIRfguPzaNbMiOCPOC1p5OwAW6MdY5L9CnGVnsdeYuRr4R64BlL_1yz3h6Yl3ZQ7XPQo3d6G."}, {"domain": ".login.taobao.com", "expiry": 1615063257, "httpOnly": true, "name": "lc", "path": "/", "sameSite": "None", "secure": true, "value": "VySm5D8GOdS2%2BAuZ5w%3D%3D"}, {"domain": ".taobao.com", "expiry": 1642737202, "httpOnly": false, "name": "thw", "path": "/", "secure": false, "value": "cn"}, {"domain": ".taobao.com", "expiry": 2243149201, "httpOnly": false, "name": "cna", "path": "/", "sameSite": "None", "secure": true, "value": "UAR7GNijvGgCAXJfeQmlDiXO"}, {"domain": ".taobao.com", "expiry": 1926993201, "httpOnly": true, "name": "enc", "path": "/", "sameSite": "None", "secure": true, "value": "XDLW%2BctEsU4%2Bl%2Bf5pIDbhMZoM4vdSuBI2cffNfmYLaWN%2FQtjRUtL7EA%2FCLsfz%2BsG92QAAPycPgCTNZmajYrfgA%3D%3D"}, {"domain": "login.taobao.com", "expiry": 1626827986, "httpOnly": false, "name": "_bl_uid", "path": "/", "secure": false, "value": "b6kjRkeC7mgkXh4emcsqa7e1e6h2"}, {"domain": ".taobao.com", "expiry": 1628045509, "httpOnly": false, "name": "tfstk", "path": "/", "secure": false, "value": "cP5CBJVqUDmC5EwrTwaZTQye_OR5Z8o6SJtNR9z8YdIY73bCiMG2cFuhEcG9HF1.."}, {"domain": ".taobao.com", "expiry": 1612508850, "httpOnly": false, "name": "lLtC1_", "path": "/", "sameSite": "None", "secure": true, "value": "1"}, {"domain": ".taobao.com", "expiry": 1620298308, "httpOnly": false, "name": "t", "path": "/", "sameSite": "None", "secure": true, "value": "89003899a9cb1b1f918b740e4b154586"}, {"domain": ".taobao.com", "expiry": 1628045509, "httpOnly": false, "name": "isg", "path": "/", "secure": false, "value": "BK6u9CDlQoUGJomLoML7aC3x_wRwr3KpP5MQDNh3G7Ftu08VUz3VuPs5dydXY2rB"}, {"domain": ".taobao.com", "expiry": 1643994001, "httpOnly": false, "name": "hng", "path": "/", "sameSite": "None", "secure": true, "value": "CN%7Czh-CN%7CCNY%7C156"}]